gmexcelhandler/__init__.py
gmfakerdata/__init__.py
gmfakerdata/china_address.py
gmfakerdata/getidcard.py
gmfakerdata/getrandomdata.py
gmfakerdata/sucreditcode.py
gmmysql/__init__.py
gmmysql/mysqlexe.py
gmmysql/utils/__init__.py
gmmysql/utils/yamlhandler.py
gmsofttest/__init__.py
gmsofttest/aes_utils.py
gmsofttest/china_address.py
gmsofttest/getrandomdata.py
gmsofttest/gm_assert_utils.py
gmsofttest/gm_demo.py
gmsofttest/gm_excel_utils.py
gmsofttest/gm_exec_python_def.py
gmsofttest/gm_exec_svn_conf_yaml.py
gmsofttest/gm_file_upload_utils.py
gmsofttest/gm_format_params.py
gmsofttest/gm_login2_utils-203045.py
gmsofttest/gm_login2_utils.py
gmsofttest/gm_login_into_utils.py
gmsofttest/gm_login_utils.py
gmsofttest/gm_oauth_utils.py
gmsofttest/gm_parse_response.py
gmsofttest/gm_parse_response_utils.py
gmsofttest/gm_randomdata.py
gmsofttest/gm_randomdata_utils.py
gmsofttest/gm_request_utils.py
gmsofttest/gm_second_verify.py
gmsofttest/gm_sqlconn.py
gmsofttest/gm_sqlconn_utils.py
gmsofttest/gm_stock_enum.py
gmsofttest/gm_sucreditcode_utils.py
gmsofttest/gm_timestamp.py
gmsofttest/gm_timestamp_utils.py
gmsofttest/gm_translate_utils.py
gmsofttest/gm_verify_list_bool.py
gmsofttest/gm_yaml_process_utils.py
gmsofttest/ha.py
gmsofttest/loggerhandler.py
gmsofttest/mysqlconn.py
gmsofttest/mytst.py
gmsofttest/run1.py
gmverifyhandler/__init__.py
gmverifyhandler/bye.py
gmsofttest-0.0.77.dist-info/LICENSE
gmsofttest-0.0.77.dist-info/METADATA
gmsofttest-0.0.77.dist-info/WHEEL
gmsofttest-0.0.77.dist-info/top_level.txt
gmsofttest-0.0.77.dist-info/RECORD
