Metadata-Version: 2.1
Name: gmsofttest
Version: 0.0.77
Summary: 大家软件内部测试技术线支撑工具
Home-page: https://www.gec123.com
Author: gmsoft1997
Author-email: uph4rmt@dingtalk.com
Project-URL: Bug Tracker, https://www.gpwbeta.com
Classifier: Programming Language :: Python :: 3
Classifier: License :: OSI Approved :: MIT License
Classifier: Operating System :: OS Independent
Requires-Python: >=3.6
License-File: LICENSE
